{
    "format_version": "1.8.0",
    "render_controllers": 
    {
        "controller.render.fr_fnaf1_sign_emissive": 
        {
            "geometry": "geometry.default",
            "materials": 
            [
                {
                    "*": "material.default"
                }
            ],
            "textures": 
            [
                "texture.default"
            ],
			"uv_anim": {
				"offset": [
					0,
					"math.mod(math.floor(query.life_time*1.3),2)/2"
				],
				"scale": [
					1,
					"0.5"
				]
			}
        }
    }
}